sugardata/__init__.py
sugardata/api.py
sugardata/concepts.py
sugardata/sentiment.py
sugardata/components/__init__.py
sugardata/components/factory.py
sugardata/components/standard_chain_builder.py
sugardata/components/translator.py
sugardata/models/__init__.py
sugardata/models/llms/__init__.py
sugardata/models/llms/factory.py
sugardata/tasks/__init__.py
sugardata/tasks/base.py
sugardata/tasks/sentiment/__init__.py
sugardata/tasks/sentiment/augment_async.py
sugardata/tasks/sentiment/augment_sync.py
sugardata/tasks/sentiment/generate_async.py
sugardata/tasks/sentiment/generate_sync.py
sugardata/tasks/sentiment/prompts.py
sugardata/tasks/sentiment/schemas.py
sugardata/tasks/sentiment/service.py
sugardata/tasks/sentiment/service_absa.py
sugardata/utility/__init__.py
sugardata/utility/concepts.py
sugardata/utility/config.py
sugardata/utility/draw.py
sugardata/utility/dynamic.py
sugardata/utility/tapas.py
sugardata/utility/translate.py
sugardata-0.0.4.dist-info/METADATA
sugardata-0.0.4.dist-info/WHEEL
sugardata-0.0.4.dist-info/top_level.txt
sugardata-0.0.4.dist-info/RECORD
